Workbook
Name HORIZONTE: Parametros!$B$2
Name WACC: Parametros!$B$3
Name INFLACION: Parametros!$B$4
Name CAPEX: Parametros!$B$5
Name CAPEX0: Parametros!$B$6
Name CAPEX1: Parametros!$B$7
Name ANIO_REP: Parametros!$B$8
Name COSTO_REP: Parametros!$B$9
Name VALOR_TERRENO: Parametros!$B$10
Name ING_H2_1: Parametros!$B$11
Name ING_O2_1: Parametros!$B$12
Name ING_FV_1: Parametros!$B$13
Name ING_EV_1: Parametros!$B$14
Name G_H2: Parametros!$B$15
Name G_O2: Parametros!$B$16
Name G_FV: Parametros!$B$17
Name G_EV: Parametros!$B$18
Name OPEX_BASE_1: Parametros!$B$19
Name G_OPEX_BASE: Parametros!$B$20
Name OPEX_LOGH2_1: Parametros!$B$21
Name G_OPEX_LOGH2: Parametros!$B$22
Name OPEX_TRATO2_1: Parametros!$B$23
Name G_OPEX_TRATO2: Parametros!$B$24
Name ANIO_OP: Parametros!$B$25
Name RESERVA_PCT: Parametros!$B$26
Name TASA_CRED: Parametros!$B$27
Name ING_H2_BASE: Escenarios_v4!$B$2
Name ING_O2_BASE: Escenarios_v4!$B$3
Name ING_FV_BASE: Escenarios_v4!$B$4
Name ING_EV_BASE: Escenarios_v4!$B$5
Name OPEX_BASE_BASE: Escenarios_v4!$B$6
Name LOGH2_BASE: Escenarios_v4!$B$7
Name TRATO2_BASE: Escenarios_v4!$B$8
Name f_H2: Escenarios_v4!$K$2
Name f_O2: Escenarios_v4!$K$3
Name f_FV: Escenarios_v4!$K$4
Name f_EV: Escenarios_v4!$K$5
Name f_OPEX_BASE: Escenarios_v4!$K$6
Name f_LOGH2: Escenarios_v4!$K$7
Name f_TRATO2: Escenarios_v4!$K$8

Sheet Parametros
A1: Descripción | B1: Valor | C1: Unidad / Nota
A2: Horizonte (años) | B2: 15 | C2: años
A3: Tasa de descuento (WACC) | B3: 0.08 | C3: porcentaje
A4: Inflación | B4: 0.04 | C4: porcentaje
A5: CAPEX total inicial (MXN) | B5: 84300000 | C5: Incluye terreno (60% año 0 / 40% año 1)
A6: Distribución CAPEX año 0 | B6: 0.6 | C6: porcentaje
A7: Distribución CAPEX año 1 | B7: 0.4 | C7: porcentaje
A8: Año reemplazo SAE | B8: 10 | C8: año
A9: Costo reemplazo SAE (MXN) | B9: 4000000
A10: Valor residual terreno (MXN, año N) | B10: 81000000 | C10: año final
A11: Ingresos H2 Año operativo 1 (MXN) | B11: =ING_H2_BASE*f_H2 | C11: +2%/año
A12: Ingresos O2 Año operativo 1 (MXN) | B12: =ING_O2_BASE*f_O2 | C12: +2%/año
A13: Ingresos FV/red Año operativo 1 (MXN) | B13: =ING_FV_BASE*f_FV | C13: -0.7%/año (FV=1.2 MW)
A14: Ingresos carga EV Año operativo 1 (MXN) | B14: =ING_EV_BASE*f_EV | C14: +2%/año
A15: Crecimiento H2 | B15: 0.02 | C15: porcentaje
A16: Crecimiento O2 | B16: 0.02 | C16: porcentaje
A17: Crecimiento FV/red | B17: -0.007 | C17: porcentaje
A18: Crecimiento carga EV | B18: 0.02 | C18: porcentaje
A19: OPEX Base Año operativo 1 (MXN) | B19: =OPEX_BASE_BASE*f_OPEX_BASE | C19: +3%/año
A20: Crecimiento OPEX Base | B20: 0.03 | C20: porcentaje
A21: OPEX Logística H2 Año op 1 (MXN) | B21: =LOGH2_BASE*f_LOGH2 | C21: +3%/año
A22: Crecimiento OPEX Logística H2 | B22: 0.03 | C22: porcentaje
A23: OPEX Tratamiento O2 Año op 1 (MXN) | B23: =TRATO2_BASE*f_TRATO2 | C23: +3%/año
A24: Crecimiento OPEX Tratamiento O2 | B24: 0.03 | C24: porcentaje
A25: Año inicio de operación | B25: 2 | C25: año (0 y 1 = inversión)
A26: Reserva liquidez (% OPEX Total) | B26: 0.2 | C26: optimización flujo de caja
A27: Tasa interés línea de crédito | B27: 0.06 | C27: porcentaje

Sheet Escenarios_v4
A1: Parámetro | B1: Valor Base (Año op 1) | C1: Unidad/Nota | E1: Selector de escenario | G1: Lista de escenarios | J1: Multiplicadores activos
A2: ING_H2_BASE | B2: 12600000 | C2: MXN/año | E2: Base | G2: Optimista | J2: f_H2 | K2: =INDEX($B$13:$H$15, MATCH($E$2,$A$13:$A$15,0), 2)
A3: ING_O2_BASE | B3: 6720000 | C3: MXN/año | G3: Base | J3: f_O2 | K3: =INDEX($B$13:$H$15, MATCH($E$2,$A$13:$A$15,0), 3)
A4: ING_FV_BASE | B4: 2740000 | C4: MXN/año (FV=1.2 MW) | G4: Conservador | J4: f_FV | K4: =INDEX($B$13:$H$15, MATCH($E$2,$A$13:$A$15,0), 4)
A5: ING_EV_BASE | B5: 800000 | C5: MXN/año | J5: f_EV | K5: =INDEX($B$13:$H$15, MATCH($E$2,$A$13:$A$15,0), 5)
A6: OPEX_BASE_BASE | B6: 2600000 | C6: MXN/año | J6: f_OPEX_BASE | K6: =INDEX($B$13:$H$15, MATCH($E$2,$A$13:$A$15,0), 6)
A7: LOGH2_BASE | B7: 4900000 | C7: MXN/año | J7: f_LOGH2 | K7: =INDEX($B$13:$H$15, MATCH($E$2,$A$13:$A$15,0), 7)
A8: TRATO2_BASE | B8: 2200000 | C8: MXN/año | J8: f_TRATO2 | K8: =INDEX($B$13:$H$15, MATCH($E$2,$A$13:$A$15,0), 8)
A11: Multiplicadores por escenario
A12: Escenario | B12: f_H2 | C12: f_O2 | D12: f_FV | E12: f_EV | F12: f_OPEX_BASE | G12: f_LOGH2 | H12: f_TRATO2
A13: Optimista | B13: 1.1333333 | C13: 1.2 | D13: 1.1 | E13: 1.1 | F13: 0.95 | G13: 0.85 | H13: 0.9
A14: Base | B14: 1 | C14: 1 | D14: 1 | E14: 1 | F14: 1 | G14: 1 | H14: 1
A15: Conservador | B15: 0.86666667 | C15: 0.8 | D15: 0.9 | E15: 0.9 | F15: 1.05 | G15: 1.15 | H15: 1.1

Sheet Flujo_Base
A1: Año | B1: Ingresos H2 | C1: Ingresos O2 | D1: Ingresos FV/red | E1: Ingresos EV | F1: Ingresos totales | G1: OPEX Base | H1: OPEX Log H2 | I1: OPEX Trat O2 | J1: OPEX Total | K1: CAPEX/Reemplazos | L1: Valor residual | M1: Flujo neto | N1: Factor descuento | O1: Flujo descontado | P1: VAN acumulado
A2: 0 | B2: =0 | C2: =0 | D2: =0 | E2: =0 | F2: =0 | G2: =0 | H2: =0 | I2: =0 | J2: =0 | K2: =CAPEX*CAPEX0 | L2: =0 | M2: =F2-J2-K2+L2 | N2: =(1+WACC)^A2 | O2: =M2/N2 | P2: =O2
A3: 1 | B3: =IF(A3<ANIO_OP,0,ING_H2_1*(1+G_H2)^(A3-ANIO_OP)) | C3: =IF(A3<ANIO_OP,0,ING_O2_1*(1+G_O2)^(A3-ANIO_OP)) | D3: =IF(A3<ANIO_OP,0,ING_FV_1*(1+G_FV)^(A3-ANIO_OP)) | E3: =IF(A3<ANIO_OP,0,ING_EV_1*(1+G_EV)^(A3-ANIO_OP)) | F3: =SUM(B3:E3) | G3: =IF(A3<ANIO_OP,0,OPEX_BASE_1*(1+G_OPEX_BASE)^(A3-ANIO_OP)) | H3: =IF(A3<ANIO_OP,0,OPEX_LOGH2_1*(1+G_OPEX_LOGH2)^(A3-ANIO_OP)) | I3: =IF(A3<ANIO_OP,0,OPEX_TRATO2_1*(1+G_OPEX_TRATO2)^(A3-ANIO_OP)) | J3: =G3+H3+I3 | K3: =IF(A3=1,CAPEX*CAPEX1,IF(A3=ANIO_REP,COSTO_REP,0)) | L3: =IF(A3=HORIZONTE,VALOR_TERRENO,0) | M3: =F3-J3-K3+L3 | N3: =(1+WACC)^A3 | O3: =M3/N3 | P3: =P2+O3
A4: 2 | B4: =IF(A4<ANIO_OP,0,ING_H2_1*(1+G_H2)^(A4-ANIO_OP)) | C4: =IF(A4<ANIO_OP,0,ING_O2_1*(1+G_O2)^(A4-ANIO_OP)) | D4: =IF(A4<ANIO_OP,0,ING_FV_1*(1+G_FV)^(A4-ANIO_OP)) | E4: =IF(A4<ANIO_OP,0,ING_EV_1*(1+G_EV)^(A4-ANIO_OP)) | F4: =SUM(B4:E4) | G4: =IF(A4<ANIO_OP,0,OPEX_BASE_1*(1+G_OPEX_BASE)^(A4-ANIO_OP)) | H4: =IF(A4<ANIO_OP,0,OPEX_LOGH2_1*(1+G_OPEX_LOGH2)^(A4-ANIO_OP)) | I4: =IF(A4<ANIO_OP,0,OPEX_TRATO2_1*(1+G_OPEX_TRATO2)^(A4-ANIO_OP)) | J4: =G4+H4+I4 | K4: =IF(A4=1,CAPEX*CAPEX1,IF(A4=ANIO_REP,COSTO_REP,0)) | L4: =IF(A4=HORIZONTE,VALOR_TERRENO,0) | M4: =F4-J4-K4+L4 | N4: =(1+WACC)^A4 | O4: =M4/N4 | P4: =P3+O4
A5: 3 | B5: =IF(A5<ANIO_OP,0,ING_H2_1*(1+G_H2)^(A5-ANIO_OP)) | C5: =IF(A5<ANIO_OP,0,ING_O2_1*(1+G_O2)^(A5-ANIO_OP)) | D5: =IF(A5<ANIO_OP,0,ING_FV_1*(1+G_FV)^(A5-ANIO_OP)) | E5: =IF(A5<ANIO_OP,0,ING_EV_1*(1+G_EV)^(A5-ANIO_OP)) | F5: =SUM(B5:E5) | G5: =IF(A5<ANIO_OP,0,OPEX_BASE_1*(1+G_OPEX_BASE)^(A5-ANIO_OP)) | H5: =IF(A5<ANIO_OP,0,OPEX_LOGH2_1*(1+G_OPEX_LOGH2)^(A5-ANIO_OP)) | I5: =IF(A5<ANIO_OP,0,OPEX_TRATO2_1*(1+G_OPEX_TRATO2)^(A5-ANIO_OP)) | J5: =G5+H5+I5 | K5: =IF(A5=1,CAPEX*CAPEX1,IF(A5=ANIO_REP,COSTO_REP,0)) | L5: =IF(A5=HORIZONTE,VALOR_TERRENO,0) | M5: =F5-J5-K5+L5 | N5: =(1+WACC)^A5 | O5: =M5/N5 | P5: =P4+O5
A6: 4 | B6: =IF(A6<ANIO_OP,0,ING_H2_1*(1+G_H2)^(A6-ANIO_OP)) | C6: =IF(A6<ANIO_OP,0,ING_O2_1*(1+G_O2)^(A6-ANIO_OP)) | D6: =IF(A6<ANIO_OP,0,ING_FV_1*(1+G_FV)^(A6-ANIO_OP)) | E6: =IF(A6<ANIO_OP,0,ING_EV_1*(1+G_EV)^(A6-ANIO_OP)) | F6: =SUM(B6:E6) | G6: =IF(A6<ANIO_OP,0,OPEX_BASE_1*(1+G_OPEX_BASE)^(A6-ANIO_OP)) | H6: =IF(A6<ANIO_OP,0,OPEX_LOGH2_1*(1+G_OPEX_LOGH2)^(A6-ANIO_OP)) | I6: =IF(A6<ANIO_OP,0,OPEX_TRATO2_1*(1+G_OPEX_TRATO2)^(A6-ANIO_OP)) | J6: =G6+H6+I6 | K6: =IF(A6=1,CAPEX*CAPEX1,IF(A6=ANIO_REP,COSTO_REP,0)) | L6: =IF(A6=HORIZONTE,VALOR_TERRENO,0) | M6: =F6-J6-K6+L6 | N6: =(1+WACC)^A6 | O6: =M6/N6 | P6: =P5+O6
A7: 5 | B7: =IF(A7<ANIO_OP,0,ING_H2_1*(1+G_H2)^(A7-ANIO_OP)) | C7: =IF(A7<ANIO_OP,0,ING_O2_1*(1+G_O2)^(A7-ANIO_OP)) | D7: =IF(A7<ANIO_OP,0,ING_FV_1*(1+G_FV)^(A7-ANIO_OP)) | E7: =IF(A7<ANIO_OP,0,ING_EV_1*(1+G_EV)^(A7-ANIO_OP)) | F7: =SUM(B7:E7) | G7: =IF(A7<ANIO_OP,0,OPEX_BASE_1*(1+G_OPEX_BASE)^(A7-ANIO_OP)) | H7: =IF(A7<ANIO_OP,0,OPEX_LOGH2_1*(1+G_OPEX_LOGH2)^(A7-ANIO_OP)) | I7: =IF(A7<ANIO_OP,0,OPEX_TRATO2_1*(1+G_OPEX_TRATO2)^(A7-ANIO_OP)) | J7: =G7+H7+I7 | K7: =IF(A7=1,CAPEX*CAPEX1,IF(A7=ANIO_REP,COSTO_REP,0)) | L7: =IF(A7=HORIZONTE,VALOR_TERRENO,0) | M7: =F7-J7-K7+L7 | N7: =(1+WACC)^A7 | O7: =M7/N7 | P7: =P6+O7
A8: 6 | B8: =IF(A8<ANIO_OP,0,ING_H2_1*(1+G_H2)^(A8-ANIO_OP)) | C8: =IF(A8<ANIO_OP,0,ING_O2_1*(1+G_O2)^(A8-ANIO_OP)) | D8: =IF(A8<ANIO_OP,0,ING_FV_1*(1+G_FV)^(A8-ANIO_OP)) | E8: =IF(A8<ANIO_OP,0,ING_EV_1*(1+G_EV)^(A8-ANIO_OP)) | F8: =SUM(B8:E8) | G8: =IF(A8<ANIO_OP,0,OPEX_BASE_1*(1+G_OPEX_BASE)^(A8-ANIO_OP)) | H8: =IF(A8<ANIO_OP,0,OPEX_LOGH2_1*(1+G_OPEX_LOGH2)^(A8-ANIO_OP)) | I8: =IF(A8<ANIO_OP,0,OPEX_TRATO2_1*(1+G_OPEX_TRATO2)^(A8-ANIO_OP)) | J8: =G8+H8+I8 | K8: =IF(A8=1,CAPEX*CAPEX1,IF(A8=ANIO_REP,COSTO_REP,0)) | L8: =IF(A8=HORIZONTE,VALOR_TERRENO,0) | M8: =F8-J8-K8+L8 | N8: =(1+WACC)^A8 | O8: =M8/N8 | P8: =P7+O8
A9: 7 | B9: =IF(A9<ANIO_OP,0,ING_H2_1*(1+G_H2)^(A9-ANIO_OP)) | C9: =IF(A9<ANIO_OP,0,ING_O2_1*(1+G_O2)^(A9-ANIO_OP)) | D9: =IF(A9<ANIO_OP,0,ING_FV_1*(1+G_FV)^(A9-ANIO_OP)) | E9: =IF(A9<ANIO_OP,0,ING_EV_1*(1+G_EV)^(A9-ANIO_OP)) | F9: =SUM(B9:E9) | G9: =IF(A9<ANIO_OP,0,OPEX_BASE_1*(1+G_OPEX_BASE)^(A9-ANIO_OP)) | H9: =IF(A9<ANIO_OP,0,OPEX_LOGH2_1*(1+G_OPEX_LOGH2)^(A9-ANIO_OP)) | I9: =IF(A9<ANIO_OP,0,OPEX_TRATO2_1*(1+G_OPEX_TRATO2)^(A9-ANIO_OP)) | J9: =G9+H9+I9 | K9: =IF(A9=1,CAPEX*CAPEX1,IF(A9=ANIO_REP,COSTO_REP,0)) | L9: =IF(A9=HORIZONTE,VALOR_TERRENO,0) | M9: =F9-J9-K9+L9 | N9: =(1+WACC)^A9 | O9: =M9/N9 | P9: =P8+O9
A10: 8 | B10: =IF(A10<ANIO_OP,0,ING_H2_1*(1+G_H2)^(A10-ANIO_OP)) | C10: =IF(A10<ANIO_OP,0,ING_O2_1*(1+G_O2)^(A10-ANIO_OP)) | D10: =IF(A10<ANIO_OP,0,ING_FV_1*(1+G_FV)^(A10-ANIO_OP)) | E10: =IF(A10<ANIO_OP,0,ING_EV_1*(1+G_EV)^(A10-ANIO_OP)) | F10: =SUM(B10:E10) | G10: =IF(A10<ANIO_OP,0,OPEX_BASE_1*(1+G_OPEX_BASE)^(A10-ANIO_OP)) | H10: =IF(A10<ANIO_OP,0,OPEX_LOGH2_1*(1+G_OPEX_LOGH2)^(A10-ANIO_OP)) | I10: =IF(A10<ANIO_OP,0,OPEX_TRATO2_1*(1+G_OPEX_TRATO2)^(A10-ANIO_OP)) | J10: =G10+H10+I10 | K10: =IF(A10=1,CAPEX*CAPEX1,IF(A10=ANIO_REP,COSTO_REP,0)) | L10: =IF(A10=HORIZONTE,VALOR_TERRENO,0) | M10: =F10-J10-K10+L10 | N10: =(1+WACC)^A10 | O10: =M10/N10 | P10: =P9+O10
A11: 9 | B11: =IF(A11<ANIO_OP,0,ING_H2_1*(1+G_H2)^(A11-ANIO_OP)) | C11: =IF(A11<ANIO_OP,0,ING_O2_1*(1+G_O2)^(A11-ANIO_OP)) | D11: =IF(A11<ANIO_OP,0,ING_FV_1*(1+G_FV)^(A11-ANIO_OP)) | E11: =IF(A11<ANIO_OP,0,ING_EV_1*(1+G_EV)^(A11-ANIO_OP)) | F11: =SUM(B11:E11) | G11: =IF(A11<ANIO_OP,0,OPEX_BASE_1*(1+G_OPEX_BASE)^(A11-ANIO_OP)) | H11: =IF(A11<ANIO_OP,0,OPEX_LOGH2_1*(1+G_OPEX_LOGH2)^(A11-ANIO_OP)) | I11: =IF(A11<ANIO_OP,0,OPEX_TRATO2_1*(1+G_OPEX_TRATO2)^(A11-ANIO_OP)) | J11: =G11+H11+I11 | K11: =IF(A11=1,CAPEX*CAPEX1,IF(A11=ANIO_REP,COSTO_REP,0)) | L11: =IF(A11=HORIZONTE,VALOR_TERRENO,0) | M11: =F11-J11-K11+L11 | N11: =(1+WACC)^A11 | O11: =M11/N11 | P11: =P10+O11
A12: 10 | B12: =IF(A12<ANIO_OP,0,ING_H2_1*(1+G_H2)^(A12-ANIO_OP)) | C12: =IF(A12<ANIO_OP,0,ING_O2_1*(1+G_O2)^(A12-ANIO_OP)) | D12: =IF(A12<ANIO_OP,0,ING_FV_1*(1+G_FV)^(A12-ANIO_OP)) | E12: =IF(A12<ANIO_OP,0,ING_EV_1*(1+G_EV)^(A12-ANIO_OP)) | F12: =SUM(B12:E12) | G12: =IF(A12<ANIO_OP,0,OPEX_BASE_1*(1+G_OPEX_BASE)^(A12-ANIO_OP)) | H12: =IF(A12<ANIO_OP,0,OPEX_LOGH2_1*(1+G_OPEX_LOGH2)^(A12-ANIO_OP)) | I12: =IF(A12<ANIO_OP,0,OPEX_TRATO2_1*(1+G_OPEX_TRATO2)^(A12-ANIO_OP)) | J12: =G12+H12+I12 | K12: =IF(A12=1,CAPEX*CAPEX1,IF(A12=ANIO_REP,COSTO_REP,0)) | L12: =IF(A12=HORIZONTE,VALOR_TERRENO,0) | M12: =F12-J12-K12+L12 | N12: =(1+WACC)^A12 | O12: =M12/N12 | P12: =P11+O12
A13: 11 | B13: =IF(A13<ANIO_OP,0,ING_H2_1*(1+G_H2)^(A13-ANIO_OP)) | C13: =IF(A13<ANIO_OP,0,ING_O2_1*(1+G_O2)^(A13-ANIO_OP)) | D13: =IF(A13<ANIO_OP,0,ING_FV_1*(1+G_FV)^(A13-ANIO_OP)) | E13: =IF(A13<ANIO_OP,0,ING_EV_1*(1+G_EV)^(A13-ANIO_OP)) | F13: =SUM(B13:E13) | G13: =IF(A13<ANIO_OP,0,OPEX_BASE_1*(1+G_OPEX_BASE)^(A13-ANIO_OP)) | H13: =IF(A13<ANIO_OP,0,OPEX_LOGH2_1*(1+G_OPEX_LOGH2)^(A13-ANIO_OP)) | I13: =IF(A13<ANIO_OP,0,OPEX_TRATO2_1*(1+G_OPEX_TRATO2)^(A13-ANIO_OP)) | J13: =G13+H13+I13 | K13: =IF(A13=1,CAPEX*CAPEX1,IF(A13=ANIO_REP,COSTO_REP,0)) | L13: =IF(A13=HORIZONTE,VALOR_TERRENO,0) | M13: =F13-J13-K13+L13 | N13: =(1+WACC)^A13 | O13: =M13/N13 | P13: =P12+O13
A14: 12 | B14: =IF(A14<ANIO_OP,0,ING_H2_1*(1+G_H2)^(A14-ANIO_OP)) | C14: =IF(A14<ANIO_OP,0,ING_O2_1*(1+G_O2)^(A14-ANIO_OP)) | D14: =IF(A14<ANIO_OP,0,ING_FV_1*(1+G_FV)^(A14-ANIO_OP)) | E14: =IF(A14<ANIO_OP,0,ING_EV_1*(1+G_EV)^(A14-ANIO_OP)) | F14: =SUM(B14:E14) | G14: =IF(A14<ANIO_OP,0,OPEX_BASE_1*(1+G_OPEX_BASE)^(A14-ANIO_OP)) | H14: =IF(A14<ANIO_OP,0,OPEX_LOGH2_1*(1+G_OPEX_LOGH2)^(A14-ANIO_OP)) | I14: =IF(A14<ANIO_OP,0,OPEX_TRATO2_1*(1+G_OPEX_TRATO2)^(A14-ANIO_OP)) | J14: =G14+H14+I14 | K14: =IF(A14=1,CAPEX*CAPEX1,IF(A14=ANIO_REP,COSTO_REP,0)) | L14: =IF(A14=HORIZONTE,VALOR_TERRENO,0) | M14: =F14-J14-K14+L14 | N14: =(1+WACC)^A14 | O14: =M14/N14 | P14: =P13+O14
... A17: 15 | B17: =IF(A17<ANIO_OP,0,ING_H2_1*(1+G_H2)^(A17-ANIO_OP)) | C17: =IF(A17<ANIO_OP,0,ING_O2_1*(1+G_O2)^(A17-ANIO_OP)) | D17: =IF(A17<ANIO_OP,0,ING_FV_1*(1+G_FV)^(A17-ANIO_OP)) | E17: =IF(A17<ANIO_OP,0,ING_EV_1*(1+G_EV)^(A17-ANIO_OP)) | F17: =SUM(B17:E17) | G17: =IF(A17<ANIO_OP,0,OPEX_BASE_1*(1+G_OPEX_BASE)^(A17-ANIO_OP)) | H17: =IF(A17<ANIO_OP,0,OPEX_LOGH2_1*(1+G_OPEX_LOGH2)^(A17-ANIO_OP)) | I17: =IF(A17<ANIO_OP,0,OPEX_TRATO2_1*(1+G_OPEX_TRATO2)^(A17-ANIO_OP)) | J17: =G17+H17+I17 | K17: =IF(A17=1,CAPEX*CAPEX1,IF(A17=ANIO_REP,COSTO_REP,0)) | L17: =IF(A17=HORIZONTE,VALOR_TERRENO,0) | M17: =F17-J17-K17+L17 | N17: =(1+WACC)^A17 | O17: =M17/N17 | P17: =P16+O17

Sheet Optimizacion_Flujo
A1: Año | B1: Flujo neto base | C1: OPEX Total | D1: Reserva requerida | E1: Δ Reserva | F1: Liquidez inicial | G1: Préstamo necesario | H1: Interés deuda | I1: Liquidez final | J1: Deuda acumulada
A2: 0 | B2: =Flujo_Base!M2 | C2: =Flujo_Base!J2 | D2: =C2*RESERVA_PCT | E2: =D2 | F2: =0 | G2: =MAX(0, -(F2 + B2 - E2)) | H2: =0 | I2: =F2 + B2 - E2 + G2 - H2 | J2: =G2
A3: 1 | B3: =Flujo_Base!M3 | C3: =Flujo_Base!J3 | D3: =C3*RESERVA_PCT | E3: =D3-D2 | F3: =I2 | G3: =MAX(0, -(F3 + B3 - E3)) | H3: =J2*TASA_CRED | I3: =F3 + B3 - E3 + G3 - H3 | J3: =J2 + G3 + H3
A4: 2 | B4: =Flujo_Base!M4 | C4: =Flujo_Base!J4 | D4: =C4*RESERVA_PCT | E4: =D4-D3 | F4: =I3 | G4: =MAX(0, -(F4 + B4 - E4)) | H4: =J3*TASA_CRED | I4: =F4 + B4 - E4 + G4 - H4 | J4: =J3 + G4 + H4
A5: 3 | B5: =Flujo_Base!M5 | C5: =Flujo_Base!J5 | D5: =C5*RESERVA_PCT | E5: =D5-D4 | F5: =I4 | G5: =MAX(0, -(F5 + B5 - E5)) | H5: =J4*TASA_CRED | I5: =F5 + B5 - E5 + G5 - H5 | J5: =J4 + G5 + H5
A6: 4 | B6: =Flujo_Base!M6 | C6: =Flujo_Base!J6 | D6: =C6*RESERVA_PCT | E6: =D6-D5 | F6: =I5 | G6: =MAX(0, -(F6 + B6 - E6)) | H6: =J5*TASA_CRED | I6: =F6 + B6 - E6 + G6 - H6 | J6: =J5 + G6 + H6
A7: 5 | B7: =Flujo_Base!M7 | C7: =Flujo_Base!J7 | D7: =C7*RESERVA_PCT | E7: =D7-D6 | F7: =I6 | G7: =MAX(0, -(F7 + B7 - E7)) | H7: =J6*TASA_CRED | I7: =F7 + B7 - E7 + G7 - H7 | J7: =J6 + G7 + H7
A8: 6 | B8: =Flujo_Base!M8 | C8: =Flujo_Base!J8 | D8: =C8*RESERVA_PCT | E8: =D8-D7 | F8: =I7 | G8: =MAX(0, -(F8 + B8 - E8)) | H8: =J7*TASA_CRED | I8: =F8 + B8 - E8 + G8 - H8 | J8: =J7 + G8 + H8
A9: 7 | B9: =Flujo_Base!M9 | C9: =Flujo_Base!J9 | D9: =C9*RESERVA_PCT | E9: =D9-D8 | F9: =I8 | G9: =MAX(0, -(F9 + B9 - E9)) | H9: =J8*TASA_CRED | I9: =F9 + B9 - E9 + G9 - H9 | J9: =J8 + G9 + H9
A10: 8 | B10: =Flujo_Base!M10 | C10: =Flujo_Base!J10 | D10: =C10*RESERVA_PCT | E10: =D10-D9 | F10: =I9 | G10: =MAX(0, -(F10 + B10 - E10)) | H10: =J9*TASA_CRED | I10: =F10 + B10 - E10 + G10 - H10 | J10: =J9 + G10 + H10
A11: 9 | B11: =Flujo_Base!M11 | C11: =Flujo_Base!J11 | D11: =C11*RESERVA_PCT | E11: =D11-D10 | F11: =I10 | G11: =MAX(0, -(F11 + B11 - E11)) | H11: =J10*TASA_CRED | I11: =F11 + B11 - E11 + G11 - H11 | J11: =J10 + G11 + H11
A12: 10 | B12: =Flujo_Base!M12 | C12: =Flujo_Base!J12 | D12: =C12*RESERVA_PCT | E12: =D12-D11 | F12: =I11 | G12: =MAX(0, -(F12 + B12 - E12)) | H12: =J11*TASA_CRED | I12: =F12 + B12 - E12 + G12 - H12 | J12: =J11 + G12 + H12
A13: 11 | B13: =Flujo_Base!M13 | C13: =Flujo_Base!J13 | D13: =C13*RESERVA_PCT | E13: =D13-D12 | F13: =I12 | G13: =MAX(0, -(F13 + B13 - E13)) | H13: =J12*TASA_CRED | I13: =F13 + B13 - E13 + G13 - H13 | J13: =J12 + G13 + H13
A14: 12 | B14: =Flujo_Base!M14 | C14: =Flujo_Base!J14 | D14: =C14*RESERVA_PCT | E14: =D14-D13 | F14: =I13 | G14: =MAX(0, -(F14 + B14 - E14)) | H14: =J13*TASA_CRED | I14: =F14 + B14 - E14 + G14 - H14 | J14: =J13 + G14 + H14
... A17: 15 | B17: =Flujo_Base!M17 | C17: =Flujo_Base!J17 | D17: =C17*RESERVA_PCT | E17: =D17-D16 | F17: =I16 | G17: =MAX(0, -(F17 + B17 - E17)) | H17: =J16*TASA_CRED | I17: =F17 + B17 - E17 + G17 - H17 | J17: =J16 + G17 + H17

Sheet Indicadores
A1: Año | B1: VAN acumulado (Flujo_Base) | C1: TIR acumulada
A2: 0 | B2: =Flujo_Base!P2 | C2: =IF(A2=0,NA(),IRR(Flujo_Base!M$2:INDEX(Flujo_Base!M:M, A2+2)))
A3: 1 | B3: =Flujo_Base!P3 | C3: =IF(A3=0,NA(),IRR(Flujo_Base!M$2:INDEX(Flujo_Base!M:M, A3+2)))
A4: 2 | B4: =Flujo_Base!P4 | C4: =IF(A4=0,NA(),IRR(Flujo_Base!M$2:INDEX(Flujo_Base!M:M, A4+2)))
A5: 3 | B5: =Flujo_Base!P5 | C5: =IF(A5=0,NA(),IRR(Flujo_Base!M$2:INDEX(Flujo_Base!M:M, A5+2)))
A6: 4 | B6: =Flujo_Base!P6 | C6: =IF(A6=0,NA(),IRR(Flujo_Base!M$2:INDEX(Flujo_Base!M:M, A6+2)))
A7: 5 | B7: =Flujo_Base!P7 | C7: =IF(A7=0,NA(),IRR(Flujo_Base!M$2:INDEX(Flujo_Base!M:M, A7+2)))
A8: 6 | B8: =Flujo_Base!P8 | C8: =IF(A8=0,NA(),IRR(Flujo_Base!M$2:INDEX(Flujo_Base!M:M, A8+2)))
A9: 7 | B9: =Flujo_Base!P9 | C9: =IF(A9=0,NA(),IRR(Flujo_Base!M$2:INDEX(Flujo_Base!M:M, A9+2)))
A10: 8 | B10: =Flujo_Base!P10 | C10: =IF(A10=0,NA(),IRR(Flujo_Base!M$2:INDEX(Flujo_Base!M:M, A10+2)))
A11: 9 | B11: =Flujo_Base!P11 | C11: =IF(A11=0,NA(),IRR(Flujo_Base!M$2:INDEX(Flujo_Base!M:M, A11+2)))
A12: 10 | B12: =Flujo_Base!P12 | C12: =IF(A12=0,NA(),IRR(Flujo_Base!M$2:INDEX(Flujo_Base!M:M, A12+2)))
A13: 11 | B13: =Flujo_Base!P13 | C13: =IF(A13=0,NA(),IRR(Flujo_Base!M$2:INDEX(Flujo_Base!M:M, A13+2)))
... A17: 15 | B17: =Flujo_Base!P17 | C17: =IF(A17=0,NA(),IRR(Flujo_Base!M$2:INDEX(Flujo_Base!M:M, A17+2)))

Sheet Dashboard
A1: Resumen Ejecutivo – ElectroHub (v4.1a con logística H2/O2, FV=1.2 MW y escenarios)

Sheet KPIs_Escenarios
A1: Escenario | B1: VAN (MXN) | C1: TIR | D1: Payback (años) | E1: PI
A2: Año | B2: Flujo_Optimista | C2: Flujo_Base | D2: Flujo_Conservador | G2: Optimista | H2: Base | I2: Conservador
A3: 0 | B3: =IF(A3<ANIO_OP,0,(Escenarios_v4!$B$2*G$3*(1+G_H2)^(A3-ANIO_OP)+Escenarios_v4!$B$3*G$4*(1+G_O2)^(A3-ANIO_OP)+Escenarios_v4!$B$4*G$5*(1+G_FV)^(A3-ANIO_OP)+Escenarios_v4!$B$5*G$6*(1+G_EV)^(A3-ANIO_OP))-(Escenarios_v4!$B$6*G$7*(1+G_OPEX_BASE)^(A3-ANIO_OP)+Escenarios_v4!$B$7*G$8*(1+G_OPEX_LOGH2)^(A3-ANIO_OP)+Escenarios_v4!$B$8*G$9*(1+G_OPEX_TRATO2)^(A3-ANIO_OP)))+IF(A3=0,CAPEX*CAPEX0,IF(A3=1,CAPEX*CAPEX1,IF(A3=ANIO_REP,COSTO_REP,0)))*(-1)+IF(A3=HORIZONTE,VALOR_TERRENO,0)) | C3: =IF(A3<ANIO_OP,0,(Escenarios_v4!$B$2*H$3*(1+G_H2)^(A3-ANIO_OP)+Escenarios_v4!$B$3*H$4*(1+G_O2)^(A3-ANIO_OP)+Escenarios_v4!$B$4*H$5*(1+G_FV)^(A3-ANIO_OP)+Escenarios_v4!$B$5*H$6*(1+G_EV)^(A3-ANIO_OP))-(Escenarios_v4!$B$6*H$7*(1+G_OPEX_BASE)^(A3-ANIO_OP)+Escenarios_v4!$B$7*H$8*(1+G_OPEX_LOGH2)^(A3-ANIO_OP)+Escenarios_v4!$B$8*H$9*(1+G_OPEX_TRATO2)^(A3-ANIO_OP)))+IF(A3=0,CAPEX*CAPEX0,IF(A3=1,CAPEX*CAPEX1,IF(A3=ANIO_REP,COSTO_REP,0)))*(-1)+IF(A3=HORIZONTE,VALOR_TERRENO,0)) | D3: =IF(A3<ANIO_OP,0,(Escenarios_v4!$B$2*I$3*(1+G_H2)^(A3-ANIO_OP)+Escenarios_v4!$B$3*I$4*(1+G_O2)^(A3-ANIO_OP)+Escenarios_v4!$B$4*I$5*(1+G_FV)^(A3-ANIO_OP)+Escenarios_v4!$B$5*I$6*(1+G_EV)^(A3-ANIO_OP))-(Escenarios_v4!$B$6*I$7*(1+G_OPEX_BASE)^(A3-ANIO_OP)+Escenarios_v4!$B$7*I$8*(1+G_OPEX_LOGH2)^(A3-ANIO_OP)+Escenarios_v4!$B$8*I$9*(1+G_OPEX_TRATO2)^(A3-ANIO_OP)))+IF(A3=0,CAPEX*CAPEX0,IF(A3=1,CAPEX*CAPEX1,IF(A3=ANIO_REP,COSTO_REP,0)))*(-1)+IF(A3=HORIZONTE,VALOR_TERRENO,0)) | G3: =INDEX(Escenarios_v4!$B$13:$H$15, MATCH($G$2,Escenarios_v4!$A$13:$A$15,0), 2) | H3: 1 | I3: =INDEX(Escenarios_v4!$B$13:$H$15, MATCH($I$2,Escenarios_v4!$A$13:$A$15,0), 2)
A4: 1 | B4: =IF(A4<ANIO_OP,0,(Escenarios_v4!$B$2*G$3*(1+G_H2)^(A4-ANIO_OP)+Escenarios_v4!$B$3*G$4*(1+G_O2)^(A4-ANIO_OP)+Escenarios_v4!$B$4*G$5*(1+G_FV)^(A4-ANIO_OP)+Escenarios_v4!$B$5*G$6*(1+G_EV)^(A4-ANIO_OP))-(Escenarios_v4!$B$6*G$7*(1+G_OPEX_BASE)^(A4-ANIO_OP)+Escenarios_v4!$B$7*G$8*(1+G_OPEX_LOGH2)^(A4-ANIO_OP)+Escenarios_v4!$B$8*G$9*(1+G_OPEX_TRATO2)^(A4-ANIO_OP)))+IF(A4=0,CAPEX*CAPEX0,IF(A4=1,CAPEX*CAPEX1,IF(A4=ANIO_REP,COSTO_REP,0)))*(-1)+IF(A4=HORIZONTE,VALOR_TERRENO,0)) | C4: =IF(A4<ANIO_OP,0,(Escenarios_v4!$B$2*H$3*(1+G_H2)^(A4-ANIO_OP)+Escenarios_v4!$B$3*H$4*(1+G_O2)^(A4-ANIO_OP)+Escenarios_v4!$B$4*H$5*(1+G_FV)^(A4-ANIO_OP)+Escenarios_v4!$B$5*H$6*(1+G_EV)^(A4-ANIO_OP))-(Escenarios_v4!$B$6*H$7*(1+G_OPEX_BASE)^(A4-ANIO_OP)+Escenarios_v4!$B$7*H$8*(1+G_OPEX_LOGH2)^(A4-ANIO_OP)+Escenarios_v4!$B$8*H$9*(1+G_OPEX_TRATO2)^(A4-ANIO_OP)))+IF(A4=0,CAPEX*CAPEX0,IF(A4=1,CAPEX*CAPEX1,IF(A4=ANIO_REP,COSTO_REP,0)))*(-1)+IF(A4=HORIZONTE,VALOR_TERRENO,0)) | D4: =IF(A4<ANIO_OP,0,(Escenarios_v4!$B$2*I$3*(1+G_H2)^(A4-ANIO_OP)+Escenarios_v4!$B$3*I$4*(1+G_O2)^(A4-ANIO_OP)+Escenarios_v4!$B$4*I$5*(1+G_FV)^(A4-ANIO_OP)+Escenarios_v4!$B$5*I$6*(1+G_EV)^(A4-ANIO_OP))-(Escenarios_v4!$B$6*I$7*(1+G_OPEX_BASE)^(A4-ANIO_OP)+Escenarios_v4!$B$7*I$8*(1+G_OPEX_LOGH2)^(A4-ANIO_OP)+Escenarios_v4!$B$8*I$9*(1+G_OPEX_TRATO2)^(A4-ANIO_OP)))+IF(A4=0,CAPEX*CAPEX0,IF(A4=1,CAPEX*CAPEX1,IF(A4=ANIO_REP,COSTO_REP,0)))*(-1)+IF(A4=HORIZONTE,VALOR_TERRENO,0)) | G4: =INDEX(Escenarios_v4!$B$13:$H$15, MATCH($G$2,Escenarios_v4!$A$13:$A$15,0), 3) | H4: 1 | I4: =INDEX(Escenarios_v4!$B$13:$H$15, MATCH($I$2,Escenarios_v4!$A$13:$A$15,0), 3)
A5: 2 | B5: =IF(A5<ANIO_OP,0,(Escenarios_v4!$B$2*G$3*(1+G_H2)^(A5-ANIO_OP)+Escenarios_v4!$B$3*G$4*(1+G_O2)^(A5-ANIO_OP)+Escenarios_v4!$B$4*G$5*(1+G_FV)^(A5-ANIO_OP)+Escenarios_v4!$B$5*G$6*(1+G_EV)^(A5-ANIO_OP))-(Escenarios_v4!$B$6*G$7*(1+G_OPEX_BASE)^(A5-ANIO_OP)+Escenarios_v4!$B$7*G$8*(1+G_OPEX_LOGH2)^(A5-ANIO_OP)+Escenarios_v4!$B$8*G$9*(1+G_OPEX_TRATO2)^(A5-ANIO_OP)))+IF(A5=0,CAPEX*CAPEX0,IF(A5=1,CAPEX*CAPEX1,IF(A5=ANIO_REP,COSTO_REP,0)))*(-1)+IF(A5=HORIZONTE,VALOR_TERRENO,0)) | C5: =IF(A5<ANIO_OP,0,(Escenarios_v4!$B$2*H$3*(1+G_H2)^(A5-ANIO_OP)+Escenarios_v4!$B$3*H$4*(1+G_O2)^(A5-ANIO_OP)+Escenarios_v4!$B$4*H$5*(1+G_FV)^(A5-ANIO_OP)+Escenarios_v4!$B$5*H$6*(1+G_EV)^(A5-ANIO_OP))-(Escenarios_v4!$B$6*H$7*(1+G_OPEX_BASE)^(A5-ANIO_OP)+Escenarios_v4!$B$7*H$8*(1+G_OPEX_LOGH2)^(A5-ANIO_OP)+Escenarios_v4!$B$8*H$9*(1+G_OPEX_TRATO2)^(A5-ANIO_OP)))+IF(A5=0,CAPEX*CAPEX0,IF(A5=1,CAPEX*CAPEX1,IF(A5=ANIO_REP,COSTO_REP,0)))*(-1)+IF(A5=HORIZONTE,VALOR_TERRENO,0)) | D5: =IF(A5<ANIO_OP,0,(Escenarios_v4!$B$2*I$3*(1+G_H2)^(A5-ANIO_OP)+Escenarios_v4!$B$3*I$4*(1+G_O2)^(A5-ANIO_OP)+Escenarios_v4!$B$4*I$5*(1+G_FV)^(A5-ANIO_OP)+Escenarios_v4!$B$5*I$6*(1+G_EV)^(A5-ANIO_OP))-(Escenarios_v4!$B$6*I$7*(1+G_OPEX_BASE)^(A5-ANIO_OP)+Escenarios_v4!$B$7*I$8*(1+G_OPEX_LOGH2)^(A5-ANIO_OP)+Escenarios_v4!$B$8*I$9*(1+G_OPEX_TRATO2)^(A5-ANIO_OP)))+IF(A5=0,CAPEX*CAPEX0,IF(A5=1,CAPEX*CAPEX1,IF(A5=ANIO_REP,COSTO_REP,0)))*(-1)+IF(A5=HORIZONTE,VALOR_TERRENO,0)) | G5: =INDEX(Escenarios_v4!$B$13:$H$15, MATCH($G$2,Escenarios_v4!$A$13:$A$15,0), 4) | H5: 1 | I5: =INDEX(Escenarios_v4!$B$13:$H$15, MATCH($I$2,Escenarios_v4!$A$13:$A$15,0), 4)
A6: 3 | B6: =IF(A6<ANIO_OP,0,(Escenarios_v4!$B$2*G$3*(1+G_H2)^(A6-ANIO_OP)+Escenarios_v4!$B$3*G$4*(1+G_O2)^(A6-ANIO_OP)+Escenarios_v4!$B$4*G$5*(1+G_FV)^(A6-ANIO_OP)+Escenarios_v4!$B$5*G$6*(1+G_EV)^(A6-ANIO_OP))-(Escenarios_v4!$B$6*G$7*(1+G_OPEX_BASE)^(A6-ANIO_OP)+Escenarios_v4!$B$7*G$8*(1+G_OPEX_LOGH2)^(A6-ANIO_OP)+Escenarios_v4!$B$8*G$9*(1+G_OPEX_TRATO2)^(A6-ANIO_OP)))+IF(A6=0,CAPEX*CAPEX0,IF(A6=1,CAPEX*CAPEX1,IF(A6=ANIO_REP,COSTO_REP,0)))*(-1)+IF(A6=HORIZONTE,VALOR_TERRENO,0)) | C6: =IF(A6<ANIO_OP,0,(Escenarios_v4!$B$2*H$3*(1+G_H2)^(A6-ANIO_OP)+Escenarios_v4!$B$3*H$4*(1+G_O2)^(A6-ANIO_OP)+Escenarios_v4!$B$4*H$5*(1+G_FV)^(A6-ANIO_OP)+Escenarios_v4!$B$5*H$6*(1+G_EV)^(A6-ANIO_OP))-(Escenarios_v4!$B$6*H$7*(1+G_OPEX_BASE)^(A6-ANIO_OP)+Escenarios_v4!$B$7*H$8*(1+G_OPEX_LOGH2)^(A6-ANIO_OP)+Escenarios_v4!$B$8*H$9*(1+G_OPEX_TRATO2)^(A6-ANIO_OP)))+IF(A6=0,CAPEX*CAPEX0,IF(A6=1,CAPEX*CAPEX1,IF(A6=ANIO_REP,COSTO_REP,0)))*(-1)+IF(A6=HORIZONTE,VALOR_TERRENO,0)) | D6: =IF(A6<ANIO_OP,0,(Escenarios_v4!$B$2*I$3*(1+G_H2)^(A6-ANIO_OP)+Escenarios_v4!$B$3*I$4*(1+G_O2)^(A6-ANIO_OP)+Escenarios_v4!$B$4*I$5*(1+G_FV)^(A6-ANIO_OP)+Escenarios_v4!$B$5*I$6*(1+G_EV)^(A6-ANIO_OP))-(Escenarios_v4!$B$6*I$7*(1+G_OPEX_BASE)^(A6-ANIO_OP)+Escenarios_v4!$B$7*I$8*(1+G_OPEX_LOGH2)^(A6-ANIO_OP)+Escenarios_v4!$B$8*I$9*(1+G_OPEX_TRATO2)^(A6-ANIO_OP)))+IF(A6=0,CAPEX*CAPEX0,IF(A6=1,CAPEX*CAPEX1,IF(A6=ANIO_REP,COSTO_REP,0)))*(-1)+IF(A6=HORIZONTE,VALOR_TERRENO,0)) | G6: =INDEX(Escenarios_v4!$B$13:$H$15, MATCH($G$2,Escenarios_v4!$A$13:$A$15,0), 5) | H6: 1 | I6: =INDEX(Escenarios_v4!$B$13:$H$15, MATCH($I$2,Escenarios_v4!$A$13:$A$15,0), 5)
A7: 4 | B7: =IF(A7<ANIO_OP,0,(Escenarios_v4!$B$2*G$3*(1+G_H2)^(A7-ANIO_OP)+Escenarios_v4!$B$3*G$4*(1+G_O2)^(A7-ANIO_OP)+Escenarios_v4!$B$4*G$5*(1+G_FV)^(A7-ANIO_OP)+Escenarios_v4!$B$5*G$6*(1+G_EV)^(A7-ANIO_OP))-(Escenarios_v4!$B$6*G$7*(1+G_OPEX_BASE)^(A7-ANIO_OP)+Escenarios_v4!$B$7*G$8*(1+G_OPEX_LOGH2)^(A7-ANIO_OP)+Escenarios_v4!$B$8*G$9*(1+G_OPEX_TRATO2)^(A7-ANIO_OP)))+IF(A7=0,CAPEX*CAPEX0,IF(A7=1,CAPEX*CAPEX1,IF(A7=ANIO_REP,COSTO_REP,0)))*(-1)+IF(A7=HORIZONTE,VALOR_TERRENO,0)) | C7: =IF(A7<ANIO_OP,0,(Escenarios_v4!$B$2*H$3*(1+G_H2)^(A7-ANIO_OP)+Escenarios_v4!$B$3*H$4*(1+G_O2)^(A7-ANIO_OP)+Escenarios_v4!$B$4*H$5*(1+G_FV)^(A7-ANIO_OP)+Escenarios_v4!$B$5*H$6*(1+G_EV)^(A7-ANIO_OP))-(Escenarios_v4!$B$6*H$7*(1+G_OPEX_BASE)^(A7-ANIO_OP)+Escenarios_v4!$B$7*H$8*(1+G_OPEX_LOGH2)^(A7-ANIO_OP)+Escenarios_v4!$B$8*H$9*(1+G_OPEX_TRATO2)^(A7-ANIO_OP)))+IF(A7=0,CAPEX*CAPEX0,IF(A7=1,CAPEX*CAPEX1,IF(A7=ANIO_REP,COSTO_REP,0)))*(-1)+IF(A7=HORIZONTE,VALOR_TERRENO,0)) | D7: =IF(A7<ANIO_OP,0,(Escenarios_v4!$B$2*I$3*(1+G_H2)^(A7-ANIO_OP)+Escenarios_v4!$B$3*I$4*(1+G_O2)^(A7-ANIO_OP)+Escenarios_v4!$B$4*I$5*(1+G_FV)^(A7-ANIO_OP)+Escenarios_v4!$B$5*I$6*(1+G_EV)^(A7-ANIO_OP))-(Escenarios_v4!$B$6*I$7*(1+G_OPEX_BASE)^(A7-ANIO_OP)+Escenarios_v4!$B$7*I$8*(1+G_OPEX_LOGH2)^(A7-ANIO_OP)+Escenarios_v4!$B$8*I$9*(1+G_OPEX_TRATO2)^(A7-ANIO_OP)))+IF(A7=0,CAPEX*CAPEX0,IF(A7=1,CAPEX*CAPEX1,IF(A7=ANIO_REP,COSTO_REP,0)))*(-1)+IF(A7=HORIZONTE,VALOR_TERRENO,0)) | G7: =INDEX(Escenarios_v4!$B$13:$H$15, MATCH($G$2,Escenarios_v4!$A$13:$A$15,0), 6) | H7: 1 | I7: =INDEX(Escenarios_v4!$B$13:$H$15, MATCH($I$2,Escenarios_v4!$A$13:$A$15,0), 6)
A8: 5 | B8: =IF(A8<ANIO_OP,0,(Escenarios_v4!$B$2*G$3*(1+G_H2)^(A8-ANIO_OP)+Escenarios_v4!$B$3*G$4*(1+G_O2)^(A8-ANIO_OP)+Escenarios_v4!$B$4*G$5*(1+G_FV)^(A8-ANIO_OP)+Escenarios_v4!$B$5*G$6*(1+G_EV)^(A8-ANIO_OP))-(Escenarios_v4!$B$6*G$7*(1+G_OPEX_BASE)^(A8-ANIO_OP)+Escenarios_v4!$B$7*G$8*(1+G_OPEX_LOGH2)^(A8-ANIO_OP)+Escenarios_v4!$B$8*G$9*(1+G_OPEX_TRATO2)^(A8-ANIO_OP)))+IF(A8=0,CAPEX*CAPEX0,IF(A8=1,CAPEX*CAPEX1,IF(A8=ANIO_REP,COSTO_REP,0)))*(-1)+IF(A8=HORIZONTE,VALOR_TERRENO,0)) | C8: =IF(A8<ANIO_OP,0,(Escenarios_v4!$B$2*H$3*(1+G_H2)^(A8-ANIO_OP)+Escenarios_v4!$B$3*H$4*(1+G_O2)^(A8-ANIO_OP)+Escenarios_v4!$B$4*H$5*(1+G_FV)^(A8-ANIO_OP)+Escenarios_v4!$B$5*H$6*(1+G_EV)^(A8-ANIO_OP))-(Escenarios_v4!$B$6*H$7*(1+G_OPEX_BASE)^(A8-ANIO_OP)+Escenarios_v4!$B$7*H$8*(1+G_OPEX_LOGH2)^(A8-ANIO_OP)+Escenarios_v4!$B$8*H$9*(1+G_OPEX_TRATO2)^(A8-ANIO_OP)))+IF(A8=0,CAPEX*CAPEX0,IF(A8=1,CAPEX*CAPEX1,IF(A8=ANIO_REP,COSTO_REP,0)))*(-1)+IF(A8=HORIZONTE,VALOR_TERRENO,0)) | D8: =IF(A8<ANIO_OP,0,(Escenarios_v4!$B$2*I$3*(1+G_H2)^(A8-ANIO_OP)+Escenarios_v4!$B$3*I$4*(1+G_O2)^(A8-ANIO_OP)+Escenarios_v4!$B$4*I$5*(1+G_FV)^(A8-ANIO_OP)+Escenarios_v4!$B$5*I$6*(1+G_EV)^(A8-ANIO_OP))-(Escenarios_v4!$B$6*I$7*(1+G_OPEX_BASE)^(A8-ANIO_OP)+Escenarios_v4!$B$7*I$8*(1+G_OPEX_LOGH2)^(A8-ANIO_OP)+Escenarios_v4!$B$8*I$9*(1+G_OPEX_TRATO2)^(A8-ANIO_OP)))+IF(A8=0,CAPEX*CAPEX0,IF(A8=1,CAPEX*CAPEX1,IF(A8=ANIO_REP,COSTO_REP,0)))*(-1)+IF(A8=HORIZONTE,VALOR_TERRENO,0)) | G8: =INDEX(Escenarios_v4!$B$13:$H$15, MATCH($G$2,Escenarios_v4!$A$13:$A$15,0), 7) | H8: 1 | I8: =INDEX(Escenarios_v4!$B$13:$H$15, MATCH($I$2,Escenarios_v4!$A$13:$A$15,0), 7)
A9: 6 | B9: =IF(A9<ANIO_OP,0,(Escenarios_v4!$B$2*G$3*(1+G_H2)^(A9-ANIO_OP)+Escenarios_v4!$B$3*G$4*(1+G_O2)^(A9-ANIO_OP)+Escenarios_v4!$B$4*G$5*(1+G_FV)^(A9-ANIO_OP)+Escenarios_v4!$B$5*G$6*(1+G_EV)^(A9-ANIO_OP))-(Escenarios_v4!$B$6*G$7*(1+G_OPEX_BASE)^(A9-ANIO_OP)+Escenarios_v4!$B$7*G$8*(1+G_OPEX_LOGH2)^(A9-ANIO_OP)+Escenarios_v4!$B$8*G$9*(1+G_OPEX_TRATO2)^(A9-ANIO_OP)))+IF(A9=0,CAPEX*CAPEX0,IF(A9=1,CAPEX*CAPEX1,IF(A9=ANIO_REP,COSTO_REP,0)))*(-1)+IF(A9=HORIZONTE,VALOR_TERRENO,0)) | C9: =IF(A9<ANIO_OP,0,(Escenarios_v4!$B$2*H$3*(1+G_H2)^(A9-ANIO_OP)+Escenarios_v4!$B$3*H$4*(1+G_O2)^(A9-ANIO_OP)+Escenarios_v4!$B$4*H$5*(1+G_FV)^(A9-ANIO_OP)+Escenarios_v4!$B$5*H$6*(1+G_EV)^(A9-ANIO_OP))-(Escenarios_v4!$B$6*H$7*(1+G_OPEX_BASE)^(A9-ANIO_OP)+Escenarios_v4!$B$7*H$8*(1+G_OPEX_LOGH2)^(A9-ANIO_OP)+Escenarios_v4!$B$8*H$9*(1+G_OPEX_TRATO2)^(A9-ANIO_OP)))+IF(A9=0,CAPEX*CAPEX0,IF(A9=1,CAPEX*CAPEX1,IF(A9=ANIO_REP,COSTO_REP,0)))*(-1)+IF(A9=HORIZONTE,VALOR_TERRENO,0)) | D9: =IF(A9<ANIO_OP,0,(Escenarios_v4!$B$2*I$3*(1+G_H2)^(A9-ANIO_OP)+Escenarios_v4!$B$3*I$4*(1+G_O2)^(A9-ANIO_OP)+Escenarios_v4!$B$4*I$5*(1+G_FV)^(A9-ANIO_OP)+Escenarios_v4!$B$5*I$6*(1+G_EV)^(A9-ANIO_OP))-(Escenarios_v4!$B$6*I$7*(1+G_OPEX_BASE)^(A9-ANIO_OP)+Escenarios_v4!$B$7*I$8*(1+G_OPEX_LOGH2)^(A9-ANIO_OP)+Escenarios_v4!$B$8*I$9*(1+G_OPEX_TRATO2)^(A9-ANIO_OP)))+IF(A9=0,CAPEX*CAPEX0,IF(A9=1,CAPEX*CAPEX1,IF(A9=ANIO_REP,COSTO_REP,0)))*(-1)+IF(A9=HORIZONTE,VALOR_TERRENO,0)) | G9: =INDEX(Escenarios_v4!$B$13:$H$15, MATCH($G$2,Escenarios_v4!$A$13:$A$15,0), 8) | H9: 1 | I9: =INDEX(Escenarios_v4!$B$13:$H$15, MATCH($I$2,Escenarios_v4!$A$13:$A$15,0), 8)
A10: 7 | B10: =IF(A10<ANIO_OP,0,(Escenarios_v4!$B$2*G$3*(1+G_H2)^(A10-ANIO_OP)+Escenarios_v4!$B$3*G$4*(1+G_O2)^(A10-ANIO_OP)+Escenarios_v4!$B$4*G$5*(1+G_FV)^(A10-ANIO_OP)+Escenarios_v4!$B$5*G$6*(1+G_EV)^(A10-ANIO_OP))-(Escenarios_v4!$B$6*G$7*(1+G_OPEX_BASE)^(A10-ANIO_OP)+Escenarios_v4!$B$7*G$8*(1+G_OPEX_LOGH2)^(A10-ANIO_OP)+Escenarios_v4!$B$8*G$9*(1+G_OPEX_TRATO2)^(A10-ANIO_OP)))+IF(A10=0,CAPEX*CAPEX0,IF(A10=1,CAPEX*CAPEX1,IF(A10=ANIO_REP,COSTO_REP,0)))*(-1)+IF(A10=HORIZONTE,VALOR_TERRENO,0)) | C10: =IF(A10<ANIO_OP,0,(Escenarios_v4!$B$2*H$3*(1+G_H2)^(A10-ANIO_OP)+Escenarios_v4!$B$3*H$4*(1+G_O2)^(A10-ANIO_OP)+Escenarios_v4!$B$4*H$5*(1+G_FV)^(A10-ANIO_OP)+Escenarios_v4!$B$5*H$6*(1+G_EV)^(A10-ANIO_OP))-(Escenarios_v4!$B$6*H$7*(1+G_OPEX_BASE)^(A10-ANIO_OP)+Escenarios_v4!$B$7*H$8*(1+G_OPEX_LOGH2)^(A10-ANIO_OP)+Escenarios_v4!$B$8*H$9*(1+G_OPEX_TRATO2)^(A10-ANIO_OP)))+IF(A10=0,CAPEX*CAPEX0,IF(A10=1,CAPEX*CAPEX1,IF(A10=ANIO_REP,COSTO_REP,0)))*(-1)+IF(A10=HORIZONTE,VALOR_TERRENO,0)) | D10: =IF(A10<ANIO_OP,0,(Escenarios_v4!$B$2*I$3*(1+G_H2)^(A10-ANIO_OP)+Escenarios_v4!$B$3*I$4*(1+G_O2)^(A10-ANIO_OP)+Escenarios_v4!$B$4*I$5*(1+G_FV)^(A10-ANIO_OP)+Escenarios_v4!$B$5*I$6*(1+G_EV)^(A10-ANIO_OP))-(Escenarios_v4!$B$6*I$7*(1+G_OPEX_BASE)^(A10-ANIO_OP)+Escenarios_v4!$B$7*I$8*(1+G_OPEX_LOGH2)^(A10-ANIO_OP)+Escenarios_v4!$B$8*I$9*(1+G_OPEX_TRATO2)^(A10-ANIO_OP)))+IF(A10=0,CAPEX*CAPEX0,IF(A10=1,CAPEX*CAPEX1,IF(A10=ANIO_REP,COSTO_REP,0)))*(-1)+IF(A10=HORIZONTE,VALOR_TERRENO,0))
A11: 8 | B11: =IF(A11<ANIO_OP,0,(Escenarios_v4!$B$2*G$3*(1+G_H2)^(A11-ANIO_OP)+Escenarios_v4!$B$3*G$4*(1+G_O2)^(A11-ANIO_OP)+Escenarios_v4!$B$4*G$5*(1+G_FV)^(A11-ANIO_OP)+Escenarios_v4!$B$5*G$6*(1+G_EV)^(A11-ANIO_OP))-(Escenarios_v4!$B$6*G$7*(1+G_OPEX_BASE)^(A11-ANIO_OP)+Escenarios_v4!$B$7*G$8*(1+G_OPEX_LOGH2)^(A11-ANIO_OP)+Escenarios_v4!$B$8*G$9*(1+G_OPEX_TRATO2)^(A11-ANIO_OP)))+IF(A11=0,CAPEX*CAPEX0,IF(A11=1,CAPEX*CAPEX1,IF(A11=ANIO_REP,COSTO_REP,0)))*(-1)+IF(A11=HORIZONTE,VALOR_TERRENO,0)) | C11: =IF(A11<ANIO_OP,0,(Escenarios_v4!$B$2*H$3*(1+G_H2)^(A11-ANIO_OP)+Escenarios_v4!$B$3*H$4*(1+G_O2)^(A11-ANIO_OP)+Escenarios_v4!$B$4*H$5*(1+G_FV)^(A11-ANIO_OP)+Escenarios_v4!$B$5*H$6*(1+G_EV)^(A11-ANIO_OP))-(Escenarios_v4!$B$6*H$7*(1+G_OPEX_BASE)^(A11-ANIO_OP)+Escenarios_v4!$B$7*H$8*(1+G_OPEX_LOGH2)^(A11-ANIO_OP)+Escenarios_v4!$B$8*H$9*(1+G_OPEX_TRATO2)^(A11-ANIO_OP)))+IF(A11=0,CAPEX*CAPEX0,IF(A11=1,CAPEX*CAPEX1,IF(A11=ANIO_REP,COSTO_REP,0)))*(-1)+IF(A11=HORIZONTE,VALOR_TERRENO,0)) | D11: =IF(A11<ANIO_OP,0,(Escenarios_v4!$B$2*I$3*(1+G_H2)^(A11-ANIO_OP)+Escenarios_v4!$B$3*I$4*(1+G_O2)^(A11-ANIO_OP)+Escenarios_v4!$B$4*I$5*(1+G_FV)^(A11-ANIO_OP)+Escenarios_v4!$B$5*I$6*(1+G_EV)^(A11-ANIO_OP))-(Escenarios_v4!$B$6*I$7*(1+G_OPEX_BASE)^(A11-ANIO_OP)+Escenarios_v4!$B$7*I$8*(1+G_OPEX_LOGH2)^(A11-ANIO_OP)+Escenarios_v4!$B$8*I$9*(1+G_OPEX_TRATO2)^(A11-ANIO_OP)))+IF(A11=0,CAPEX*CAPEX0,IF(A11=1,CAPEX*CAPEX1,IF(A11=ANIO_REP,COSTO_REP,0)))*(-1)+IF(A11=HORIZONTE,VALOR_TERRENO,0))
A12: 9 | B12: =IF(A12<ANIO_OP,0,(Escenarios_v4!$B$2*G$3*(1+G_H2)^(A12-ANIO_OP)+Escenarios_v4!$B$3*G$4*(1+G_O2)^(A12-ANIO_OP)+Escenarios_v4!$B$4*G$5*(1+G_FV)^(A12-ANIO_OP)+Escenarios_v4!$B$5*G$6*(1+G_EV)^(A12-ANIO_OP))-(Escenarios_v4!$B$6*G$7*(1+G_OPEX_BASE)^(A12-ANIO_OP)+Escenarios_v4!$B$7*G$8*(1+G_OPEX_LOGH2)^(A12-ANIO_OP)+Escenarios_v4!$B$8*G$9*(1+G_OPEX_TRATO2)^(A12-ANIO_OP)))+IF(A12=0,CAPEX*CAPEX0,IF(A12=1,CAPEX*CAPEX1,IF(A12=ANIO_REP,COSTO_REP,0)))*(-1)+IF(A12=HORIZONTE,VALOR_TERRENO,0)) | C12: =IF(A12<ANIO_OP,0,(Escenarios_v4!$B$2*H$3*(1+G_H2)^(A12-ANIO_OP)+Escenarios_v4!$B$3*H$4*(1+G_O2)^(A12-ANIO_OP)+Escenarios_v4!$B$4*H$5*(1+G_FV)^(A12-ANIO_OP)+Escenarios_v4!$B$5*H$6*(1+G_EV)^(A12-ANIO_OP))-(Escenarios_v4!$B$6*H$7*(1+G_OPEX_BASE)^(A12-ANIO_OP)+Escenarios_v4!$B$7*H$8*(1+G_OPEX_LOGH2)^(A12-ANIO_OP)+Escenarios_v4!$B$8*H$9*(1+G_OPEX_TRATO2)^(A12-ANIO_OP)))+IF(A12=0,CAPEX*CAPEX0,IF(A12=1,CAPEX*CAPEX1,IF(A12=ANIO_REP,COSTO_REP,0)))*(-1)+IF(A12=HORIZONTE,VALOR_TERRENO,0)) | D12: =IF(A12<ANIO_OP,0,(Escenarios_v4!$B$2*I$3*(1+G_H2)^(A12-ANIO_OP)+Escenarios_v4!$B$3*I$4*(1+G_O2)^(A12-ANIO_OP)+Escenarios_v4!$B$4*I$5*(1+G_FV)^(A12-ANIO_OP)+Escenarios_v4!$B$5*I$6*(1+G_EV)^(A12-ANIO_OP))-(Escenarios_v4!$B$6*I$7*(1+G_OPEX_BASE)^(A12-ANIO_OP)+Escenarios_v4!$B$7*I$8*(1+G_OPEX_LOGH2)^(A12-ANIO_OP)+Escenarios_v4!$B$8*I$9*(1+G_OPEX_TRATO2)^(A12-ANIO_OP)))+IF(A12=0,CAPEX*CAPEX0,IF(A12=1,CAPEX*CAPEX1,IF(A12=ANIO_REP,COSTO_REP,0)))*(-1)+IF(A12=HORIZONTE,VALOR_TERRENO,0))
A13: 10 | B13: =IF(A13<ANIO_OP,0,(Escenarios_v4!$B$2*G$3*(1+G_H2)^(A13-ANIO_OP)+Escenarios_v4!$B$3*G$4*(1+G_O2)^(A13-ANIO_OP)+Escenarios_v4!$B$4*G$5*(1+G_FV)^(A13-ANIO_OP)+Escenarios_v4!$B$5*G$6*(1+G_EV)^(A13-ANIO_OP))-(Escenarios_v4!$B$6*G$7*(1+G_OPEX_BASE)^(A13-ANIO_OP)+Escenarios_v4!$B$7*G$8*(1+G_OPEX_LOGH2)^(A13-ANIO_OP)+Escenarios_v4!$B$8*G$9*(1+G_OPEX_TRATO2)^(A13-ANIO_OP)))+IF(A13=0,CAPEX*CAPEX0,IF(A13=1,CAPEX*CAPEX1,IF(A13=ANIO_REP,COSTO_REP,0)))*(-1)+IF(A13=HORIZONTE,VALOR_TERRENO,0)) | C13: =IF(A13<ANIO_OP,0,(Escenarios_v4!$B$2*H$3*(1+G_H2)^(A13-ANIO_OP)+Escenarios_v4!$B$3*H$4*(1+G_O2)^(A13-ANIO_OP)+Escenarios_v4!$B$4*H$5*(1+G_FV)^(A13-ANIO_OP)+Escenarios_v4!$B$5*H$6*(1+G_EV)^(A13-ANIO_OP))-(Escenarios_v4!$B$6*H$7*(1+G_OPEX_BASE)^(A13-ANIO_OP)+Escenarios_v4!$B$7*H$8*(1+G_OPEX_LOGH2)^(A13-ANIO_OP)+Escenarios_v4!$B$8*H$9*(1+G_OPEX_TRATO2)^(A13-ANIO_OP)))+IF(A13=0,CAPEX*CAPEX0,IF(A13=1,CAPEX*CAPEX1,IF(A13=ANIO_REP,COSTO_REP,0)))*(-1)+IF(A13=HORIZONTE,VALOR_TERRENO,0)) | D13: =IF(A13<ANIO_OP,0,(Escenarios_v4!$B$2*I$3*(1+G_H2)^(A13-ANIO_OP)+Escenarios_v4!$B$3*I$4*(1+G_O2)^(A13-ANIO_OP)+Escenarios_v4!$B$4*I$5*(1+G_FV)^(A13-ANIO_OP)+Escenarios_v4!$B$5*I$6*(1+G_EV)^(A13-ANIO_OP))-(Escenarios_v4!$B$6*I$7*(1+G_OPEX_BASE)^(A13-ANIO_OP)+Escenarios_v4!$B$7*I$8*(1+G_OPEX_LOGH2)^(A13-ANIO_OP)+Escenarios_v4!$B$8*I$9*(1+G_OPEX_TRATO2)^(A13-ANIO_OP)))+IF(A13=0,CAPEX*CAPEX0,IF(A13=1,CAPEX*CAPEX1,IF(A13=ANIO_REP,COSTO_REP,0)))*(-1)+IF(A13=HORIZONTE,VALOR_TERRENO,0))
A14: 11 | B14: =IF(A14<ANIO_OP,0,(Escenarios_v4!$B$2*G$3*(1+G_H2)^(A14-ANIO_OP)+Escenarios_v4!$B$3*G$4*(1+G_O2)^(A14-ANIO_OP)+Escenarios_v4!$B$4*G$5*(1+G_FV)^(A14-ANIO_OP)+Escenarios_v4!$B$5*G$6*(1+G_EV)^(A14-ANIO_OP))-(Escenarios_v4!$B$6*G$7*(1+G_OPEX_BASE)^(A14-ANIO_OP)+Escenarios_v4!$B$7*G$8*(1+G_OPEX_LOGH2)^(A14-ANIO_OP)+Escenarios_v4!$B$8*G$9*(1+G_OPEX_TRATO2)^(A14-ANIO_OP)))+IF(A14=0,CAPEX*CAPEX0,IF(A14=1,CAPEX*CAPEX1,IF(A14=ANIO_REP,COSTO_REP,0)))*(-1)+IF(A14=HORIZONTE,VALOR_TERRENO,0)) | C14: =IF(A14<ANIO_OP,0,(Escenarios_v4!$B$2*H$3*(1+G_H2)^(A14-ANIO_OP)+Escenarios_v4!$B$3*H$4*(1+G_O2)^(A14-ANIO_OP)+Escenarios_v4!$B$4*H$5*(1+G_FV)^(A14-ANIO_OP)+Escenarios_v4!$B$5*H$6*(1+G_EV)^(A14-ANIO_OP))-(Escenarios_v4!$B$6*H$7*(1+G_OPEX_BASE)^(A14-ANIO_OP)+Escenarios_v4!$B$7*H$8*(1+G_OPEX_LOGH2)^(A14-ANIO_OP)+Escenarios_v4!$B$8*H$9*(1+G_OPEX_TRATO2)^(A14-ANIO_OP)))+IF(A14=0,CAPEX*CAPEX0,IF(A14=1,CAPEX*CAPEX1,IF(A14=ANIO_REP,COSTO_REP,0)))*(-1)+IF(A14=HORIZONTE,VALOR_TERRENO,0)) | D14: =IF(A14<ANIO_OP,0,(Escenarios_v4!$B$2*I$3*(1+G_H2)^(A14-ANIO_OP)+Escenarios_v4!$B$3*I$4*(1+G_O2)^(A14-ANIO_OP)+Escenarios_v4!$B$4*I$5*(1+G_FV)^(A14-ANIO_OP)+Escenarios_v4!$B$5*I$6*(1+G_EV)^(A14-ANIO_OP))-(Escenarios_v4!$B$6*I$7*(1+G_OPEX_BASE)^(A14-ANIO_OP)+Escenarios_v4!$B$7*I$8*(1+G_OPEX_LOGH2)^(A14-ANIO_OP)+Escenarios_v4!$B$8*I$9*(1+G_OPEX_TRATO2)^(A14-ANIO_OP)))+IF(A14=0,CAPEX*CAPEX0,IF(A14=1,CAPEX*CAPEX1,IF(A14=ANIO_REP,COSTO_REP,0)))*(-1)+IF(A14=HORIZONTE,VALOR_TERRENO,0))
A15: 12 | B15: =IF(A15<ANIO_OP,0,(Escenarios_v4!$B$2*G$3*(1+G_H2)^(A15-ANIO_OP)+Escenarios_v4!$B$3*G$4*(1+G_O2)^(A15-ANIO_OP)+Escenarios_v4!$B$4*G$5*(1+G_FV)^(A15-ANIO_OP)+Escenarios_v4!$B$5*G$6*(1+G_EV)^(A15-ANIO_OP))-(Escenarios_v4!$B$6*G$7*(1+G_OPEX_BASE)^(A15-ANIO_OP)+Escenarios_v4!$B$7*G$8*(1+G_OPEX_LOGH2)^(A15-ANIO_OP)+Escenarios_v4!$B$8*G$9*(1+G_OPEX_TRATO2)^(A15-ANIO_OP)))+IF(A15=0,CAPEX*CAPEX0,IF(A15=1,CAPEX*CAPEX1,IF(A15=ANIO_REP,COSTO_REP,0)))*(-1)+IF(A15=HORIZONTE,VALOR_TERRENO,0)) | C15: =IF(A15<ANIO_OP,0,(Escenarios_v4!$B$2*H$3*(1+G_H2)^(A15-ANIO_OP)+Escenarios_v4!$B$3*H$4*(1+G_O2)^(A15-ANIO_OP)+Escenarios_v4!$B$4*H$5*(1+G_FV)^(A15-ANIO_OP)+Escenarios_v4!$B$5*H$6*(1+G_EV)^(A15-ANIO_OP))-(Escenarios_v4!$B$6*H$7*(1+G_OPEX_BASE)^(A15-ANIO_OP)+Escenarios_v4!$B$7*H$8*(1+G_OPEX_LOGH2)^(A15-ANIO_OP)+Escenarios_v4!$B$8*H$9*(1+G_OPEX_TRATO2)^(A15-ANIO_OP)))+IF(A15=0,CAPEX*CAPEX0,IF(A15=1,CAPEX*CAPEX1,IF(A15=ANIO_REP,COSTO_REP,0)))*(-1)+IF(A15=HORIZONTE,VALOR_TERRENO,0)) | D15: =IF(A15<ANIO_OP,0,(Escenarios_v4!$B$2*I$3*(1+G_H2)^(A15-ANIO_OP)+Escenarios_v4!$B$3*I$4*(1+G_O2)^(A15-ANIO_OP)+Escenarios_v4!$B$4*I$5*(1+G_FV)^(A15-ANIO_OP)+Escenarios_v4!$B$5*I$6*(1+G_EV)^(A15-ANIO_OP))-(Escenarios_v4!$B$6*I$7*(1+G_OPEX_BASE)^(A15-ANIO_OP)+Escenarios_v4!$B$7*I$8*(1+G_OPEX_LOGH2)^(A15-ANIO_OP)+Escenarios_v4!$B$8*I$9*(1+G_OPEX_TRATO2)^(A15-ANIO_OP)))+IF(A15=0,CAPEX*CAPEX0,IF(A15=1,CAPEX*CAPEX1,IF(A15=ANIO_REP,COSTO_REP,0)))*(-1)+IF(A15=HORIZONTE,VALOR_TERRENO,0))
A16: 13 | B16: =IF(A16<ANIO_OP,0,(Escenarios_v4!$B$2*G$3*(1+G_H2)^(A16-ANIO_OP)+Escenarios_v4!$B$3*G$4*(1+G_O2)^(A16-ANIO_OP)+Escenarios_v4!$B$4*G$5*(1+G_FV)^(A16-ANIO_OP)+Escenarios_v4!$B$5*G$6*(1+G_EV)^(A16-ANIO_OP))-(Escenarios_v4!$B$6*G$7*(1+G_OPEX_BASE)^(A16-ANIO_OP)+Escenarios_v4!$B$7*G$8*(1+G_OPEX_LOGH2)^(A16-ANIO_OP)+Escenarios_v4!$B$8*G$9*(1+G_OPEX_TRATO2)^(A16-ANIO_OP)))+IF(A16=0,CAPEX*CAPEX0,IF(A16=1,CAPEX*CAPEX1,IF(A16=ANIO_REP,COSTO_REP,0)))*(-1)+IF(A16=HORIZONTE,VALOR_TERRENO,0)) | C16: =IF(A16<ANIO_OP,0,(Escenarios_v4!$B$2*H$3*(1+G_H2)^(A16-ANIO_OP)+Escenarios_v4!$B$3*H$4*(1+G_O2)^(A16-ANIO_OP)+Escenarios_v4!$B$4*H$5*(1+G_FV)^(A16-ANIO_OP)+Escenarios_v4!$B$5*H$6*(1+G_EV)^(A16-ANIO_OP))-(Escenarios_v4!$B$6*H$7*(1+G_OPEX_BASE)^(A16-ANIO_OP)+Escenarios_v4!$B$7*H$8*(1+G_OPEX_LOGH2)^(A16-ANIO_OP)+Escenarios_v4!$B$8*H$9*(1+G_OPEX_TRATO2)^(A16-ANIO_OP)))+IF(A16=0,CAPEX*CAPEX0,IF(A16=1,CAPEX*CAPEX1,IF(A16=ANIO_REP,COSTO_REP,0)))*(-1)+IF(A16=HORIZONTE,VALOR_TERRENO,0)) | D16: =IF(A16<ANIO_OP,0,(Escenarios_v4!$B$2*I$3*(1+G_H2)^(A16-ANIO_OP)+Escenarios_v4!$B$3*I$4*(1+G_O2)^(A16-ANIO_OP)+Escenarios_v4!$B$4*I$5*(1+G_FV)^(A16-ANIO_OP)+Escenarios_v4!$B$5*I$6*(1+G_EV)^(A16-ANIO_OP))-(Escenarios_v4!$B$6*I$7*(1+G_OPEX_BASE)^(A16-ANIO_OP)+Escenarios_v4!$B$7*I$8*(1+G_OPEX_LOGH2)^(A16-ANIO_OP)+Escenarios_v4!$B$8*I$9*(1+G_OPEX_TRATO2)^(A16-ANIO_OP)))+IF(A16=0,CAPEX*CAPEX0,IF(A16=1,CAPEX*CAPEX1,IF(A16=ANIO_REP,COSTO_REP,0)))*(-1)+IF(A16=HORIZONTE,VALOR_TERRENO,0))
A17: 14 | B17: =IF(A17<ANIO_OP,0,(Escenarios_v4!$B$2*G$3*(1+G_H2)^(A17-ANIO_OP)+Escenarios_v4!$B$3*G$4*(1+G_O2)^(A17-ANIO_OP)+Escenarios_v4!$B$4*G$5*(1+G_FV)^(A17-ANIO_OP)+Escenarios_v4!$B$5*G$6*(1+G_EV)^(A17-ANIO_OP))-(Escenarios_v4!$B$6*G$7*(1+G_OPEX_BASE)^(A17-ANIO_OP)+Escenarios_v4!$B$7*G$8*(1+G_OPEX_LOGH2)^(A17-ANIO_OP)+Escenarios_v4!$B$8*G$9*(1+G_OPEX_TRATO2)^(A17-ANIO_OP)))+IF(A17=0,CAPEX*CAPEX0,IF(A17=1,CAPEX*CAPEX1,IF(A17=ANIO_REP,COSTO_REP,0)))*(-1)+IF(A17=HORIZONTE,VALOR_TERRENO,0)) | C17: =IF(A17<ANIO_OP,0,(Escenarios_v4!$B$2*H$3*(1+G_H2)^(A17-ANIO_OP)+Escenarios_v4!$B$3*H$4*(1+G_O2)^(A17-ANIO_OP)+Escenarios_v4!$B$4*H$5*(1+G_FV)^(A17-ANIO_OP)+Escenarios_v4!$B$5*H$6*(1+G_EV)^(A17-ANIO_OP))-(Escenarios_v4!$B$6*H$7*(1+G_OPEX_BASE)^(A17-ANIO_OP)+Escenarios_v4!$B$7*H$8*(1+G_OPEX_LOGH2)^(A17-ANIO_OP)+Escenarios_v4!$B$8*H$9*(1+G_OPEX_TRATO2)^(A17-ANIO_OP)))+IF(A17=0,CAPEX*CAPEX0,IF(A17=1,CAPEX*CAPEX1,IF(A17=ANIO_REP,COSTO_REP,0)))*(-1)+IF(A17=HORIZONTE,VALOR_TERRENO,0)) | D17: =IF(A17<ANIO_OP,0,(Escenarios_v4!$B$2*I$3*(1+G_H2)^(A17-ANIO_OP)+Escenarios_v4!$B$3*I$4*(1+G_O2)^(A17-ANIO_OP)+Escenarios_v4!$B$4*I$5*(1+G_FV)^(A17-ANIO_OP)+Escenarios_v4!$B$5*I$6*(1+G_EV)^(A17-ANIO_OP))-(Escenarios_v4!$B$6*I$7*(1+G_OPEX_BASE)^(A17-ANIO_OP)+Escenarios_v4!$B$7*I$8*(1+G_OPEX_LOGH2)^(A17-ANIO_OP)+Escenarios_v4!$B$8*I$9*(1+G_OPEX_TRATO2)^(A17-ANIO_OP)))+IF(A17=0,CAPEX*CAPEX0,IF(A17=1,CAPEX*CAPEX1,IF(A17=ANIO_REP,COSTO_REP,0)))*(-1)+IF(A17=HORIZONTE,VALOR_TERRENO,0))
A18: 15 | B18: =IF(A18<ANIO_OP,0,(Escenarios_v4!$B$2*G$3*(1+G_H2)^(A18-ANIO_OP)+Escenarios_v4!$B$3*G$4*(1+G_O2)^(A18-ANIO_OP)+Escenarios_v4!$B$4*G$5*(1+G_FV)^(A18-ANIO_OP)+Escenarios_v4!$B$5*G$6*(1+G_EV)^(A18-ANIO_OP))-(Escenarios_v4!$B$6*G$7*(1+G_OPEX_BASE)^(A18-ANIO_OP)+Escenarios_v4!$B$7*G$8*(1+G_OPEX_LOGH2)^(A18-ANIO_OP)+Escenarios_v4!$B$8*G$9*(1+G_OPEX_TRATO2)^(A18-ANIO_OP)))+IF(A18=0,CAPEX*CAPEX0,IF(A18=1,CAPEX*CAPEX1,IF(A18=ANIO_REP,COSTO_REP,0)))*(-1)+IF(A18=HORIZONTE,VALOR_TERRENO,0)) | C18: =IF(A18<ANIO_OP,0,(Escenarios_v4!$B$2*H$3*(1+G_H2)^(A18-ANIO_OP)+Escenarios_v4!$B$3*H$4*(1+G_O2)^(A18-ANIO_OP)+Escenarios_v4!$B$4*H$5*(1+G_FV)^(A18-ANIO_OP)+Escenarios_v4!$B$5*H$6*(1+G_EV)^(A18-ANIO_OP))-(Escenarios_v4!$B$6*H$7*(1+G_OPEX_BASE)^(A18-ANIO_OP)+Escenarios_v4!$B$7*H$8*(1+G_OPEX_LOGH2)^(A18-ANIO_OP)+Escenarios_v4!$B$8*H$9*(1+G_OPEX_TRATO2)^(A18-ANIO_OP)))+IF(A18=0,CAPEX*CAPEX0,IF(A18=1,CAPEX*CAPEX1,IF(A18=ANIO_REP,COSTO_REP,0)))*(-1)+IF(A18=HORIZONTE,VALOR_TERRENO,0)) | D18: =IF(A18<ANIO_OP,0,(Escenarios_v4!$B$2*I$3*(1+G_H2)^(A18-ANIO_OP)+Escenarios_v4!$B$3*I$4*(1+G_O2)^(A18-ANIO_OP)+Escenarios_v4!$B$4*I$5*(1+G_FV)^(A18-ANIO_OP)+Escenarios_v4!$B$5*I$6*(1+G_EV)^(A18-ANIO_OP))-(Escenarios_v4!$B$6*I$7*(1+G_OPEX_BASE)^(A18-ANIO_OP)+Escenarios_v4!$B$7*I$8*(1+G_OPEX_LOGH2)^(A18-ANIO_OP)+Escenarios_v4!$B$8*I$9*(1+G_OPEX_TRATO2)^(A18-ANIO_OP)))+IF(A18=0,CAPEX*CAPEX0,IF(A18=1,CAPEX*CAPEX1,IF(A18=ANIO_REP,COSTO_REP,0)))*(-1)+IF(A18=HORIZONTE,VALOR_TERRENO,0))
E19: Helper (desc & cum)
A20: KPIs por Escenario | E20: PI | F20: B_desc | G20: B_cum | H20: C_desc | I20: C_cum | J20: D_desc | K20: D_cum
A21: Optimista | B21: =NPV(WACC, B4:B19) + B3 | C21: =IRR(B3:B19) | D21: =MATCH(TRUE,INDEX(G21:G36>=0,0),0)-1 | E21: =NPV(WACC,B4:B19)/ABS(B3) | F21: =B4/(1+WACC)^E21 | G21: =IF(E21=0, F21, G20+F21) | H21: =C4/(1+WACC)^E21 | I21: =IF(E21=0, H21, I20+H21) | J21: =D4/(1+WACC)^E21 | K21: =IF(E21=0, J21, K20+J21)
A22: Base | B22: =NPV(WACC, C4:C19) + C3 | C22: =IRR(C3:C19) | D22: =MATCH(TRUE,INDEX(I21:I36>=0,0),0)-1 | E22: =NPV(WACC,C4:C19)/ABS(C3) | F22: =B5/(1+WACC)^E22 | G22: =IF(E22=0, F22, G21+F22) | H22: =C5/(1+WACC)^E22 | I22: =IF(E22=0, H22, I21+H22) | J22: =D5/(1+WACC)^E22 | K22: =IF(E22=0, J22, K21+J22)
A23: Conservador | B23: =NPV(WACC, D4:D19) + D3 | C23: =IRR(D3:D19) | D23: =MATCH(TRUE,INDEX(K21:K36>=0,0),0)-1 | E23: =NPV(WACC,D4:D19)/ABS(D3) | F23: =B6/(1+WACC)^E23 | G23: =IF(E23=0, F23, G22+F23) | H23: =C6/(1+WACC)^E23 | I23: =IF(E23=0, H23, I22+H23) | J23: =D6/(1+WACC)^E23 | K23: =IF(E23=0, J23, K22+J23)
E24: 3 | F24: =B7/(1+WACC)^E24 | G24: =IF(E24=0, F24, G23+F24) | H24: =C7/(1+WACC)^E24 | I24: =IF(E24=0, H24, I23+H24) | J24: =D7/(1+WACC)^E24 | K24: =IF(E24=0, J24, K23+J24)
E25: 4 | F25: =B8/(1+WACC)^E25 | G25: =IF(E25=0, F25, G24+F25) | H25: =C8/(1+WACC)^E25 | I25: =IF(E25=0, H25, I24+H25) | J25: =D8/(1+WACC)^E25 | K25: =IF(E25=0, J25, K24+J25)
E26: 5 | F26: =B9/(1+WACC)^E26 | G26: =IF(E26=0, F26, G25+F26) | H26: =C9/(1+WACC)^E26 | I26: =IF(E26=0, H26, I25+H26) | J26: =D9/(1+WACC)^E26 | K26: =IF(E26=0, J26, K25+J26)
E27: 6 | F27: =B10/(1+WACC)^E27 | G27: =IF(E27=0, F27, G26+F27) | H27: =C10/(1+WACC)^E27 | I27: =IF(E27=0, H27, I26+H27) | J27: =D10/(1+WACC)^E27 | K27: =IF(E27=0, J27, K26+J27)
E28: 7 | F28: =B11/(1+WACC)^E28 | G28: =IF(E28=0, F28, G27+F28) | H28: =C11/(1+WACC)^E28 | I28: =IF(E28=0, H28, I27+H28) | J28: =D11/(1+WACC)^E28 | K28: =IF(E28=0, J28, K27+J28)
E29: 8 | F29: =B12/(1+WACC)^E29 | G29: =IF(E29=0, F29, G28+F29) | H29: =C12/(1+WACC)^E29 | I29: =IF(E29=0, H29, I28+H29) | J29: =D12/(1+WACC)^E29 | K29: =IF(E29=0, J29, K28+J29)
E30: 9 | F30: =B13/(1+WACC)^E30 | G30: =IF(E30=0, F30, G29+F30) | H30: =C13/(1+WACC)^E30 | I30: =IF(E30=0, H30, I29+H30) | J30: =D13/(1+WACC)^E30 | K30: =IF(E30=0, J30, K29+J30)
E31: 10 | F31: =B14/(1+WACC)^E31 | G31: =IF(E31=0, F31, G30+F31) | H31: =C14/(1+WACC)^E31 | I31: =IF(E31=0, H31, I30+H31) | J31: =D14/(1+WACC)^E31 | K31: =IF(E31=0, J31, K30+J31)
E32: 11 | F32: =B15/(1+WACC)^E32 | G32: =IF(E32=0, F32, G31+F32) | H32: =C15/(1+WACC)^E32 | I32: =IF(E32=0, H32, I31+H32) | J32: =D15/(1+WACC)^E32 | K32: =IF(E32=0, J32, K31+J32)
E33: 12 | F33: =B16/(1+WACC)^E33 | G33: =IF(E33=0, F33, G32+F33) | H33: =C16/(1+WACC)^E33 | I33: =IF(E33=0, H33, I32+H33) | J33: =D16/(1+WACC)^E33 | K33: =IF(E33=0, J33, K32+J33)
E34: 13 | F34: =B17/(1+WACC)^E34 | G34: =IF(E34=0, F34, G33+F34) | H34: =C17/(1+WACC)^E34 | I34: =IF(E34=0, H34, I33+H34) | J34: =D17/(1+WACC)^E34 | K34: =IF(E34=0, J34, K33+J34)
E35: 14 | F35: =B18/(1+WACC)^E35 | G35: =IF(E35=0, F35, G34+F35) | H35: =C18/(1+WACC)^E35 | I35: =IF(E35=0, H35, I34+H35) | J35: =D18/(1+WACC)^E35 | K35: =IF(E35=0, J35, K34+J35)
E36: 15 | F36: =B19/(1+WACC)^E36 | G36: =IF(E36=0, F36, G35+F36) | H36: =C19/(1+WACC)^E36 | I36: =IF(E36=0, H36, I35+H36) | J36: =D19/(1+WACC)^E36 | K36: =IF(E36=0, J36, K35+J36)

Sheet Resumen_Anual
A1: Año | B1: H₂ (MXN) | C1: O₂ (MXN) | D1: FV/red (MXN) | E1: EV (MXN) | F1: Ingresos totales (MXN) | G1: OPEX Base | H1: OPEX Log H₂ | I1: OPEX Trat O₂ | J1: OPEX Total | K1: CAPEX/Reemplazos | L1: Valor residual | M1: Flujo neto | N1: VAN acumulado | O1: Liquidez final | P1: Deuda acumulada
A2: 0 | B2: =Flujo_Base!B2 | C2: =Flujo_Base!C2 | D2: =Flujo_Base!D2 | E2: =Flujo_Base!E2 | F2: =Flujo_Base!F2 | G2: =Flujo_Base!G2 | H2: =Flujo_Base!H2 | I2: =Flujo_Base!I2 | ... M2: =Flujo_Base!M2 | N2: =Flujo_Base!P2 | O2: =Optimizacion_Flujo!I2 | P2: =Optimizacion_Flujo!J2
A3: 1 | B3: =Flujo_Base!B3 | C3: =Flujo_Base!C3 | D3: =Flujo_Base!D3 | E3: =Flujo_Base!E3 | F3: =Flujo_Base!F3 | G3: =Flujo_Base!G3 | H3: =Flujo_Base!H3 | I3: =Flujo_Base!I3 | ... M3: =Flujo_Base!M3 | N3: =Flujo_Base!P3 | O3: =Optimizacion_Flujo!I3 | P3: =Optimizacion_Flujo!J3
A4: 2 | B4: =Flujo_Base!B4 | C4: =Flujo_Base!C4 | D4: =Flujo_Base!D4 | E4: =Flujo_Base!E4 | F4: =Flujo_Base!F4 | G4: =Flujo_Base!G4 | H4: =Flujo_Base!H4 | I4: =Flujo_Base!I4 | ... M4: =Flujo_Base!M4 | N4: =Flujo_Base!P4 | O4: =Optimizacion_Flujo!I4 | P4: =Optimizacion_Flujo!J4
A5: 3 | B5: =Flujo_Base!B5 | C5: =Flujo_Base!C5 | D5: =Flujo_Base!D5 | E5: =Flujo_Base!E5 | F5: =Flujo_Base!F5 | G5: =Flujo_Base!G5 | H5: =Flujo_Base!H5 | I5: =Flujo_Base!I5 | ... M5: =Flujo_Base!M5 | N5: =Flujo_Base!P5 | O5: =Optimizacion_Flujo!I5 | P5: =Optimizacion_Flujo!J5
A6: 4 | B6: =Flujo_Base!B6 | C6: =Flujo_Base!C6 | D6: =Flujo_Base!D6 | E6: =Flujo_Base!E6 | F6: =Flujo_Base!F6 | G6: =Flujo_Base!G6 | H6: =Flujo_Base!H6 | I6: =Flujo_Base!I6 | ... M6: =Flujo_Base!M6 | N6: =Flujo_Base!P6 | O6: =Optimizacion_Flujo!I6 | P6: =Optimizacion_Flujo!J6
A7: 5 | B7: =Flujo_Base!B7 | C7: =Flujo_Base!C7 | D7: =Flujo_Base!D7 | E7: =Flujo_Base!E7 | F7: =Flujo_Base!F7 | G7: =Flujo_Base!G7 | H7: =Flujo_Base!H7 | I7: =Flujo_Base!I7 | ... M7: =Flujo_Base!M7 | N7: =Flujo_Base!P7 | O7: =Optimizacion_Flujo!I7 | P7: =Optimizacion_Flujo!J7
A8: 6 | B8: =Flujo_Base!B8 | C8: =Flujo_Base!C8 | D8: =Flujo_Base!D8 | E8: =Flujo_Base!E8 | F8: =Flujo_Base!F8 | G8: =Flujo_Base!G8 | H8: =Flujo_Base!H8 | I8: =Flujo_Base!I8 | ... M8: =Flujo_Base!M8 | N8: =Flujo_Base!P8 | O8: =Optimizacion_Flujo!I8 | P8: =Optimizacion_Flujo!J8
A9: 7 | B9: =Flujo_Base!B9 | C9: =Flujo_Base!C9 | D9: =Flujo_Base!D9 | E9: =Flujo_Base!E9 | F9: =Flujo_Base!F9 | G9: =Flujo_Base!G9 | H9: =Flujo_Base!H9 | I9: =Flujo_Base!I9 | ... M9: =Flujo_Base!M9 | N9: =Flujo_Base!P9 | O9: =Optimizacion_Flujo!I9 | P9: =Optimizacion_Flujo!J9
A10: 8 | B10: =Flujo_Base!B10 | C10: =Flujo_Base!C10 | D10: =Flujo_Base!D10 | E10: =Flujo_Base!E10 | F10: =Flujo_Base!F10 | G10: =Flujo_Base!G10 | H10: =Flujo_Base!H10 | I10: =Flujo_Base!I10 | ... M10: =Flujo_Base!M10 | N10: =Flujo_Base!P10 | O10: =Optimizacion_Flujo!I10 | P10: =Optimizacion_Flujo!J10
A11: 9 | B11: =Flujo_Base!B11 | C11: =Flujo_Base!C11 | D11: =Flujo_Base!D11 | E11: =Flujo_Base!E11 | F11: =Flujo_Base!F11 | G11: =Flujo_Base!G11 | H11: =Flujo_Base!H11 | I11: =Flujo_Base!I11 | ... M11: =Flujo_Base!M11 | N11: =Flujo_Base!P11 | O11: =Optimizacion_Flujo!I11 | P11: =Optimizacion_Flujo!J11
A12: 10 | B12: =Flujo_Base!B12 | C12: =Flujo_Base!C12 | D12: =Flujo_Base!D12 | E12: =Flujo_Base!E12 | F12: =Flujo_Base!F12 | G12: =Flujo_Base!G12 | H12: =Flujo_Base!H12 | I12: =Flujo_Base!I12 | ... M12: =Flujo_Base!M12 | N12: =Flujo_Base!P12 | O12: =Optimizacion_Flujo!I12 | P12: =Optimizacion_Flujo!J12
A13: 11 | B13: =Flujo_Base!B13 | C13: =Flujo_Base!C13 | D13: =Flujo_Base!D13 | E13: =Flujo_Base!E13 | F13: =Flujo_Base!F13 | G13: =Flujo_Base!G13 | H13: =Flujo_Base!H13 | I13: =Flujo_Base!I13 | ... M13: =Flujo_Base!M13 | N13: =Flujo_Base!P13 | O13: =Optimizacion_Flujo!I13 | P13: =Optimizacion_Flujo!J13
... A17: 15 | B17: =Flujo_Base!B17 | C17: =Flujo_Base!C17 | D17: =Flujo_Base!D17 | E17: =Flujo_Base!E17 | F17: =Flujo_Base!F17 | G17: =Flujo_Base!G17 | H17: =Flujo_Base!H17 | I17: =Flujo_Base!I17 | ... M17: =Flujo_Base!M17 | N17: =Flujo_Base!P17 | O17: =Optimizacion_Flujo!I17 | P17: =Optimizacion_Flujo!J17

Sheet Seguridad_H2
A1: Parámetros de seguridad y flashback – Hidrógeno (H₂)
A3: Velocidad laminar de combustión (Su) | B3: 2.86 | C3: m/s (≈286 cm/s)
A5: Normas recomendadas
A6: ISO 5175-1 | B6: Arrestadores de retroceso (estaciones/puntos de uso)
A7: ISO 16852 | B7: Apagallamas en líneas/venteos (deflagración/detonación)
A8: NFPA 2 / CGA G-5.5 | B8: Distancias/criterios de seguridad y venteo

Sheet Instrucciones
A1: Cómo usar la plantilla v4.1a
A3: 1) Elige escenario en Escenarios_v4 (Optimista/Base/Conservador).
A4: 2) Parametros toma automáticamente los valores iniciales × multiplicadores del escenario.
A5: 3) Flujo_Base y Optimizacion_Flujo se recalculan por fórmula; no edites manualmente celdas calculadas.
A6: 4) KPIs_Escenarios compara VAN/TIR/Payback/PI de los 3 escenarios en paralelo (con payback robusto).
A7: 5) Resumen_Anual lista por año ingresos, OPEX por componente, flujo neto, VAN, liquidez y deuda.
A8: 6) Seguridad_H2 contiene el dato de flashback (Su=2.86 m/s) y normas de referencia (ISO/NFPA/CGA).
